{"_id":{"$oid":"5eaf3a4b42c736fb5e02bf5a"},"titulo":"Os Vingadores: Guerra Infinita","sinopse":"Os heróis mais poderosos da Marvel enfrentando o Thanos","duracao":120.0,"dataLancamento":{"$date":"2018-05-01T00:00:00.000Z"},"imagem":"https://www.luiztools.com.br/vingadores-gi.jpg","categorias":["Aventura","Ação"]}
{"_id":{"$oid":"5eaf3a4b42c736fb5e02bf5b"},"titulo":"Os Vingadores: Era de Ultron","sinopse":"Os heróis mais poderosos da Marvel enfrentando o Ultron","duracao":110.0,"dataLancamento":{"$date":"2016-05-01T00:00:00.000Z"},"imagem":"https://www.luiztools.com.br/vingadores-eu.jpg","categorias":["Aventura","Ação"]}
{"_id":{"$oid":"5eaf3a4b42c736fb5e02bf5c"},"titulo":"\u003c\u003c\u003c Filme do Abu \u003e\u003e\u003e","sinopse":"Os heróis mais poderosos da Marvel enfrentando o Ultron","duracao":110.0,"dataLancamento":{"$date":"2020-04-01T00:00:00.000Z"},"imagem":"https://www.luiztools.com.br/vingadores-eu.jpg","categorias":["Aventura","Ação"]}
{"_id":{"$oid":"5eaf3a4b42c736fb5e02bf5d"},"titulo":"Os Vingadores","sinopse":"Os heróis mais poderosos da Marvel enfrentando o Loki","duracao":100.0,"dataLancamento":{"$date":"2014-05-01T00:00:00.000Z"},"imagem":"https://www.luiztools.com.br/vingadores.jpg","categorias":["Aventura","Ação"]}
{"_id":{"$oid":"5eaf3a5642c736fb5e02bf5e"},"titulo":"\u003c\u003c\u003c Filme do Abu - 2\u003e\u003e\u003e","sinopse":"Os heróis mais poderosos da Marvel enfrentando o Ultron","duracao":110.0,"dataLancamento":{"$date":"2020-05-01T00:00:00.000Z"},"imagem":"https://www.luiztools.com.br/vingadores-eu.jpg","categorias":["Aventura","Ação"]}
